scikit_image-0.23.0.dist-info/METADATA
scikit_image-0.23.0.dist-info/WHEEL
scikit_image-0.23.0.dist-info/LICENSE.txt
scikit_image-0.23.0.dist-info/RECORD
skimage/conftest.py
skimage/__init__.py
skimage/py.typed
skimage/__init__.pyi
skimage/draw/_draw.cpython-311-x86_64-linux-gnu.so
skimage/draw/__init__.py
skimage/draw/_polygon2mask.py
skimage/draw/_random_shapes.py
skimage/draw/draw.py
skimage/draw/__init__.pyi
skimage/draw/draw_nd.py
skimage/draw/draw3d.py
skimage/draw/tests/test_draw.py
skimage/draw/tests/test_draw_nd.py
skimage/draw/tests/__init__.py
skimage/draw/tests/test_polygon2mask.py
skimage/draw/tests/test_draw3d.py
skimage/draw/tests/test_random_shapes.py
skimage/morphology/_skeletonize.py
skimage/morphology/max_tree.py
skimage/morphology/extrema.py
skimage/morphology/ball_decompositions.npy
skimage/morphology/binary.py
skimage/morphology/disk_decompositions.npy
skimage/morphology/_util.py
skimage/morphology/_skeletonize_3d_cy.cpython-311-x86_64-linux-gnu.so
skimage/morphology/footprints.py
skimage/morphology/grayreconstruct.py
skimage/morphology/__init__.py
skimage/morphology/_skeletonize_cy.cpython-311-x86_64-linux-gnu.so
skimage/morphology/gray.py
skimage/morphology/_extrema_cy.cpython-311-x86_64-linux-gnu.so
skimage/morphology/_convex_hull.cpython-311-x86_64-linux-gnu.so
skimage/morphology/_flood_fill_cy.cpython-311-x86_64-linux-gnu.so
skimage/morphology/misc.py
skimage/morphology/isotropic.py
skimage/morphology/_grayreconstruct.cpython-311-x86_64-linux-gnu.so
skimage/morphology/_flood_fill.py
skimage/morphology/convex_hull.py
skimage/morphology/_max_tree.cpython-311-x86_64-linux-gnu.so
skimage/morphology/tests/test_convex_hull.py
skimage/morphology/tests/test_skeletonize.py
skimage/morphology/tests/test_isotropic.py
skimage/morphology/tests/test_util.py
skimage/morphology/tests/test_footprints.py
skimage/morphology/tests/test_max_tree.py
skimage/morphology/tests/__init__.py
skimage/morphology/tests/test_reconstruction.py
skimage/morphology/tests/test_gray.py
skimage/morphology/tests/test_misc.py
skimage/morphology/tests/test_extrema.py
