Metadata-Version: 2.1
Name: scikit-image
Version: 0.23.0
Summary: Image processing in Python
Home-page: https://scikit-image.org
Maintainer-Email: scikit-image developers <skimage-core@discuss.scientific-python.org>
License: Files: *
Classifier: Development Status :: 4 - Beta
Classifier: Environment :: Console
Classifier: Intended Audience :: Developers
Classifier: Intended Audience :: Science/Research
Classifier: License :: OSI Approved :: BSD License
Classifier: Programming Language :: C
Classifier: Programming Language :: Python
Classifier: Programming Language :: Python :: 3
Classifier: Programming Language :: Python :: 3.10
Classifier: Programming Language :: Python :: 3.11
Classifier: Programming Language :: Python :: 3.12
Classifier: Programming Language :: Python :: 3 :: Only
Classifier: Topic :: Software Development :: Libraries
Classifier: Topic :: Scientific/Engineering
Classifier: Operating System :: Microsoft :: Windows
Classifier: Operating System :: POSIX
Classifier: Operating System :: Unix
Classifier: Operating System :: MacOS
Project-URL: Homepage, https://scikit-image.org
Project-URL: Documentation, https://scikit-image.org/docs/stable
Project-URL: Source, https://github.com/scikit-image/scikit-image
Project-URL: Download, https://pypi.org/project/scikit-image/#files
Project-URL: Tracker, https://github.com/scikit-image/scikit-image/issues
Requires-Python: >=3.10
Requires-Dist: numpy>=1.23
Requires-Dist: scipy>=1.9
Requires-Dist: networkx>=2.8
Requires-Dist: pillow>=9.1
Requires-Dist: imageio>=2.33
Requires-Dist: tifffile>=2022.8.12
Requires-Dist: packaging>=21
Requires-Dist: lazy-loader>=0.4
Requires-Dist: meson-python>=0.15; extra == "build"
Requires-Dist: wheel; extra == "build"
Requires-Dist: setuptools>=67; extra == "build"
Requires-Dist: packaging>=21; extra == "build"
Requires-Dist: ninja; extra == "build"
Requires-Dist: Cython>=3.0.4; extra == "build"
Requires-Dist: pythran; extra == "build"
Requires-Dist: numpy>=2.0.0rc1; extra == "build"
Requires-Dist: spin==0.8; extra == "build"
Requires-Dist: build; extra == "build"
Requires-Dist: pooch>=1.6.0; extra == "data"
Requires-Dist: pre-commit; extra == "developer"
Requires-Dist: ipython; extra == "developer"
Requires-Dist: tomli; python_version < "3.11" and extra == "developer"
Requires-Dist: sphinx>=7.2; extra == "docs"
Requires-Dist: sphinx-gallery>=0.14; extra == "docs"
Requires-Dist: numpydoc>=1.7; extra == "docs"
Requires-Dist: sphinx-copybutton; extra == "docs"
Requires-Dist: pytest-runner; extra == "docs"
Requires-Dist: matplotlib>=3.6; extra == "docs"
Requires-Dist: dask[array]>=2022.9.2; extra == "docs"
Requires-Dist: pandas>=1.5; extra == "docs"
Requires-Dist: seaborn>=0.11; extra == "docs"
Requires-Dist: pooch>=1.6; extra == "docs"
Requires-Dist: tifffile>=2022.8.12; extra == "docs"
Requires-Dist: myst-parser; extra == "docs"
Requires-Dist: ipywidgets; extra == "docs"
Requires-Dist: ipykernel; extra == "docs"
Requires-Dist: plotly>=5.10; extra == "docs"
Requires-Dist: kaleido; extra == "docs"
Requires-Dist: scikit-learn>=1.1; extra == "docs"
Requires-Dist: sphinx_design>=0.5; extra == "docs"
Requires-Dist: pydata-sphinx-theme>=0.15.2; extra == "docs"
Requires-Dist: PyWavelets>=1.1.1; extra == "docs"
Requires-Dist: pytest-doctestplus; extra == "docs"
Requires-Dist: SimpleITK; extra == "optional"
Requires-Dist: astropy>=5.0; extra == "optional"
Requires-Dist: cloudpickle>=0.2.1; extra == "optional"
Requires-Dist: dask[array]>=2021.1.0; extra == "optional"
Requires-Dist: matplotlib>=3.6; extra == "optional"
Requires-Dist: pooch>=1.6.0; extra == "optional"
Requires-Dist: pyamg; extra == "optional"
Requires-Dist: PyWavelets>=1.1.1; extra == "optional"
Requires-Dist: scikit-learn>=1.1; extra == "optional"
Requires-Dist: asv; extra == "test"
Requires-Dist: numpydoc>=1.7; extra == "test"
Requires-Dist: pooch>=1.6.0; extra == "test"
Requires-Dist: pytest>=7.0; extra == "test"
Requires-Dist: pytest-cov>=2.11.0; extra == "test"
Requires-Dist: pytest-localserver; extra == "test"
Requires-Dist: pytest-faulthandler; extra == "test"
Requires-Dist: pytest-doctestplus; extra == "test"
Provides-Extra: build
Provides-Extra: data
Provides-Extra: developer
Provides-Extra: docs
Provides-Extra: optional
Provides-Extra: test
